kairospay/__init__.py
kairospay/binancepay.py
kairospay/mlive.py
kairospay/models/np.py
kairospay/monnify.py
kairospay/nowpayment.py
kairospay/np/core/base.py
kairospay/np/core/decorators.py
kairospay/np/currencies.py
kairospay/np/payment.py
kairospay/np/payout.py
kairospay-2.1.0.dist-info/LICENSE
kairospay-2.1.0.dist-info/METADATA
kairospay-2.1.0.dist-info/WHEEL
kairospay-2.1.0.dist-info/RECORD
